biosemi/__init__.py
biosemi/real_time_app.py
biosemi/example/__init__.py
biosemi/example/test_client_and_server.py
biosemi/main/__init__.py
biosemi/main/biosemiTcpRealTime.py
biosemi/main/main_window.py
biosemi/main/py_averager/__init__.py
biosemi/main/py_averager/javerager_test.py
biosemi/main/py_averager/weightedAverage.py
biosemi/test_server/__init__.py
biosemi/test_server/test_server.py
biosemi_realtime-1.0.9.dist-info/LICENSE.txt
biosemi_realtime-1.0.9.dist-info/METADATA
biosemi_realtime-1.0.9.dist-info/WHEEL
biosemi_realtime-1.0.9.dist-info/top_level.txt
biosemi_realtime-1.0.9.dist-info/RECORD
